pyscipopt/relax.pxi
pyscipopt/nodesel.pxi
pyscipopt/benders.pxi
pyscipopt/presol.pxi
pyscipopt/scip.pxd
pyscipopt/sepa.pxi
pyscipopt/reader.pxi
pyscipopt/scip.pxi
pyscipopt/matrix.pxi
pyscipopt/__init__.py
pyscipopt/scip.pyx
pyscipopt/_version.py
pyscipopt/scip.cpython-39-x86_64-linux-gnu.so
pyscipopt/conshdlr.pxi
pyscipopt/branchrule.pxi
pyscipopt/lp.pxi
pyscipopt/pricer.pxi
pyscipopt/benderscut.pxi
pyscipopt/heuristic.pxi
pyscipopt/cutsel.pxi
pyscipopt/event.pxi
pyscipopt/propagator.pxi
pyscipopt/Multidict.py
pyscipopt/expr.pxi
pyscipopt/recipes/primal_dual_evolution.py
pyscipopt/recipes/piecewise.py
pyscipopt/recipes/__init__.py
pyscipopt/recipes/infeasibilities.py
pyscipopt/recipes/nonlinear.py
pyscipopt.libs/libquadmath-828275a7.so.0.0.0
pyscipopt.libs/libgfortran-8f1e9814.so.5.0.0
pyscipopt.libs/libscip-8b62cb5e.so.9.2
pyscipopt-5.5.0.dist-info/top_level.txt
pyscipopt-5.5.0.dist-info/RECORD
pyscipopt-5.5.0.dist-info/METADATA
pyscipopt-5.5.0.dist-info/WHEEL
pyscipopt-5.5.0.dist-info/licenses/LICENSE
