Metadata-Version: 2.1
Name: PySCIPOpt
Version: 5.5.0
Summary: Python interface and modeling environment for SCIP
Home-page: https://github.com/SCIP-Interfaces/PySCIPOpt
Author: Zuse Institute Berlin
Author-email: Zuse Institute Berlin <scip@zib.de>
License: MIT
Project-URL: Homepage, https://github.com/SCIP-Interfaces/PySCIPOpt
Classifier: Development Status :: 4 - Beta
Classifier: Intended Audience :: Education
Classifier: Intended Audience :: Science/Research
Classifier: License :: OSI Approved :: MIT License
Classifier: Programming Language :: Cython
Classifier: Programming Language :: Python :: 3
Classifier: Topic :: Scientific/Engineering :: Mathematics
Requires-Python: >=3.8
License-File: LICENSE
Requires-Dist: numpy >=1.16.0
